topacedo/__init__.py
topacedo/density.py
topacedo/main.py
topacedo/recluster.py
topacedo-0.2.10.dist-info/LICENSE.md
topacedo-0.2.10.dist-info/METADATA
topacedo-0.2.10.dist-info/WHEEL
topacedo-0.2.10.dist-info/top_level.txt
topacedo-0.2.10.dist-info/RECORD
