Metadata-Version: 2.1
Name: topacedo
Version: 0.2.10
Summary: topacedo
Home-page: https://github.com/parashardhapola/topacedo
Author: Parashar Dhapola
Author-email: parashar.dhapola@gmail.com
Keywords: store
Classifier: Development Status :: 4 - Beta
Classifier: Natural Language :: English
Classifier: Operating System :: POSIX :: Linux
Classifier: Programming Language :: Python :: 3
Classifier: Programming Language :: Python :: 3.7
Classifier: Programming Language :: Python :: 3.8
License-File: LICENSE.md
Requires-Dist: numpy
Requires-Dist: pandas
Requires-Dist: scipy
Requires-Dist: tqdm
Requires-Dist: numba
Requires-Dist: networkx
Requires-Dist: pcst-fast
